Workbook
Name _2Excel_BuiltIn_Print_Area_1: Contract!$C:$V
Name _3Excel_BuiltIn_Print_Area_3: 'Order Form'!$A$1:$AM$60
Name Address: Contract!$F$10
Name AdministrativeFee: Contract!$T$74
Name AlumStuccoRemovalRange: 'Order Form'!$AP$31:$AP$54
Name AmtFinanced: Contract!$T$78
Name ArgonGasQty: Contract!$M$16
Name BalanceToCollect: Contract!$T$77
Name BayWindowQty: Contract!$M$53
Name BeigeColor: 'Order Form'!$C$138
Name BeigeColorQty: Contract!$M$19
Name CapTrim: 'Order Form'!$C$152
Name CasementAwning1: 'Order Form'!$C$164
Name CasementAwning2: 'Order Form'!$C$165
Name CasementAwning3: 'Order Form'!$C$166
Name CasementAwningAll: 'Order Form'!$C$167
Name CasementAwningQty: Contract!$C$23
Name CellPhone: Contract!$S$11
Name City: Contract!$F$11
Name ColonialContouredGridsQty: Contract!$M$31
Name ColorRange: 'Order Form'!$E$31:$E$54
Name CustId: Contract!$K$10
Name CustName: Contract!$F$9
Name CustomJambQty: Contract!$M$47
Name CustomTrim: 'Order Form'!$C$151
Name CustomTrimQty: Contract!$M$49
Name DoorGridRange: 'Order Form'!$AW$31:$AW$54
Name DoorLe: 'Order Form'!$C$157
Name DoorLee: 'Order Form'!$C$158
Name DoorLeeRange: 'Order Form'!$AV$31:$AV$54
Name DoorLeRange: 'Order Form'!$AU$31:$AU$54
Name DoubleHung4000Price: Contract!$H$16
Name DoubleHung4000Qty: Contract!$C$16
Name DoubleHung6000Price: Contract!$H$15
Name DoubleHung6000Qty: Contract!$C$15
Name DoubleLocksQty: Contract!$M$15
Name EmailAddress: Contract!$J$9
Name EnergyStarQty: Contract!$M$37
Name EnergyStarTGQty: Contract!$M$38
Name EnergyStarTKQty: Contract!$M$39
Name ESQty: Contract!$Y$37
Name ESVPArgonQty: Contract!$Y$38
Name ESVPQty: Contract!$Y$39
Name ExteriorCappingQty: Contract!$M$48
Name ExternalColorQty: Contract!$M$32
Name FinishAndTrim: 'Order Form'!$C$153
Name FoamInsulationWrapQty: Contract!$M$17
Name FullScreen: 'Order Form'!$C$137
Name FullScreenPrice: Contract!$T$14
Name FullScreenQty: Contract!$M$14
Name FullScreenRange: 'Order Form'!$AA$31:$AA$54
Name GlassOptionLe: 'Order Form'!$C$141
Name GlassOptionLee: 'Order Form'!$C$140
Name GlassOptionRange: 'Order Form'!$P$31:$P$54
Name GridsDoor: 'Order Form'!$C$160
Name GridsPatioDoorQty: Contract!$C$52
Name GridStyleRange: 'Order Form'!$R$31:$R$54
Name GridsWindow: 'Order Form'!$C$142
Name HalfScreenQty: Contract!$M$13
Name HomePhone: Contract!$S$9

Sheet Contract
M1: Window and Patio Door Contract
M2: Locations:
O4: Baton Rouge | Q4: 8405 Airline Hwy, Baton Rouge, LA 70815
O5: New Orleans | Q5: 8814 Veterans Blvd, Metairie, LA 70003
O6: Lafayette | Q6: 3148 Ambassador Caffery Pkwy, Suite 4, Lafayette, LA 70506
O8: Complete Job? | Q8: N | U8: Remaining # of Windows? | Y8: Y
B9: Name: | H9: Email: | Y9: N
B10: Address: | J10: Customer ID #: | Q10: Primary #:
B11: City: | G11: State: | H11: LA | I11: Zip Code: | Q11: Secondary #:
E12: Windows | M12: QTY | O12: Options | T12: AMT | V12: TOTAL
C13: QTY | E13: Double Hung | H13: AMT | J13: TOTAL | M13: =IF(ESVPQty=0,"",ESVPQty) | O13: Extruded Aluminum Half Screen | T13: Incl. | V13: INCL
E14: Series Model # | O14: Extruded Aluminum Full Screen | T14: 22 | V14: =IF(M14="","",M14*T14) | Y14: 12
E15: 4000 DH Fusion Weld | G15: 3001 | H15: 385 | J15: =IF(C15="","",C15*H15) | M15: =IF(ESVPQty=0,"",ESVPQty) | O15: Double Locks ( > 29" wide) | T15: Incl. | V15: INCL | Y15: 22
E16: 4000 DH Foam Enhanced | G16: 3001-FE | H16: 410 | J16: =IF(C16="","",C16*H16) | M16: =IF(ESVPArgonQty=0,"",ESVPArgonQty) | O16: Argon Gas | T16: 21 | V16: INCL
E17: (Steel Reinforced White Windows) | M17: =IF(EnergyStarTKQty=0,"",EnergyStarTKQty) | O17: Krypton Gas (TK2 Plus Elite) | T17: 119 | V17: =IF(M17="","",IF((M17-EnergyStarTKQty)>0,(M17-EnergyStarTKQty)*T17,0))
M18: =IF(ESVPQty=0,"",ESVPQty) | O18: Foam Insulation Wrap | T18: 15 | V18: INCL
E19: Other Styles | O19: Beige / Clay Color | T19: 52 | V19: =IF(M19="","",M19*T19)
E20: Picture Window | G20: 3004 | H20: 449 | J20: =IF(C20="","",C20*H20) | O20: Wood Grain - Inside Surface | T20: 90 | V20: =IF(M20="","",M20*T20)
E21: 2 Lite Slider | G21: 3002 | H21: 449 | J21: =IF(C21="","",C21*H21) | M21: =IF(ValuePlusQty="","",ValuePlusQty) | O21: SolarZone Low-E-Glass | T21: 90 | V21: =IF(M21="","",IF((M21-ValuePlusQty)>0,(M21-ValuePlusQty)*T21,0))
E22: 3 Lite Slider | G22: 3003 | H22: 610 | J22: =IF(C22="","",C22*H22) | M22: =IF(ESQty>0,ESQty,"") | O22: SolarZone Elite Low-E-Glass | T22: 110 | V22: INCL
E23: Casement / Awning | H23: 529 | J23: =IF(C23="","",C23*H23) | O23: Tempered Glass Sq Ft. | T23: $7/Sq.ft | V23: =IF(M23="","",(M23)*7)
E24: Double Casement | H24: 1018 | J24: =IF(C24="","",C24*H24) | O24: Obscure Glass ( Rain / Std. ) | T24: 30 | V24: =IF(M24="","",(M24)*T24)
E25: Foam Enhanced Upcharge - Add | H25: 25 | J25: =IF(C25="","",C25*H25) | M25: =IF(ESVPQty=0,"",ESVPQty) | O25: Lifetime Glass Break Warranty | T25: 39 | V25: INCL
E26: Single Hung Special Shape W/ | H26: 619 | J26: =IF(C26="","",C26*H26) | O26: Nail Fin | T26: 10 | V26: =IF(M26="","",M26*T26)
F27: Operating Sash | J27: =IF(C27="","",C27*H27) | O27: Oriel/Cottage Style 60/40 | T27: 36 | V27: =IF(M27="","",M27*T27)
E28: Specialty Windows | J28: =IF(C28="","",C28*H28) | O28: Flat / Contoured Grids | T28: 45 | V28: =IF(M28="","",M28*T28)
E29: ______________________________ | J29: =IF(C29="","",C29*H29) | O29: Exterior Color (Exterior Surface Only) | T29: 250 | V29: =IF(M29="","",M29*T29)
E30: ______________________________ | J30: =IF(C30="","",C30*H30)
E31: ______________________________ | J31: =IF(C31="","",C31*H31) | O31: Specialty Window Options | V31: =IF(M31="","",M31*T29)
J32: =IF(C32="","",C32*H32) | O32: _______________________________ | V32: =IF(M32="","",M32*T32)
B33: Our windows carry the Good Housekeeping seal of approval, and carry an AMMA Gold label certification, ensuring our window system is of highest quality. All of our windows have double strength and DP rated glass. | O33: _______________________________ | V33: =IF(M33="","",M33*T33)
O34: _______________________________ | V34: =IF(M34="","",M34*T34)
O36: Value Plus Package | T36: 104 | V36: =IF(M36="","",M36*T36) | Y36: =SUM(C15:C24)+C26+SUM(C28:C32)+SUM(C43:C46)+SUM(C57:C60) -> 0
O37: Energy Star Pkg | T37: 124 | V37: =IF(M37="","",M37*T37) | Y37: =EnergyStarQty+EnergyStarTGQty+EnergyStarTKQty -> 0
O38: TG2 PriME Elite- Energy Star Most | T38: 289 | V38: =IF(M38="","",M38*T38) | Y38: =SUM(M36:M38) -> 0
B39: PRE 1978 BUILT HOMES (Federal Lead Containment Law) | O39: TK2 Plus Elite- Energy Star Most | T39: 394 | V39: =IF(M39="","",M39*T39) | Y39: =SUM(M36:M39) -> 0
M40: QTY | O40: Additional Labor Charges | V40: TOTAL
B41: My home was built in the year: | H41: Initials: | O41: Remove Storm Window | T41: 10 | V41: =IF(M41="","",M41*T41)
C42: QTY | F42: DOORS | J42: TOTAL | O42: Window Removal | T42: 60 | V42: =IF(M42="","",M42*T42)
E43: Vinyl Rolling Door 6' 6406 (2p) | H43: 1409 | J43: =IF(C43="","",C43*H43) | O43: Remove Steel Window | T43: 70 | V43: =IF(M43="","",M43*T43) | AD43: 125
E44: Vinyl Rolling Door 8' 6408 (2p) | H44: 1645 | J44: =IF(C44="","",C44*H44) | O44: Remove Aluminum In Stucco | T44: 90 | V44: =IF(M44="","",M44*T44) | AD44: 75
E45: Vinyl Rolling Door 9' 6409 (3p) | H45: 1871 | J45: =IF(C45="","",C45*H45) | O45: Install Mullion for multi-unit | T45: 30 | V45: =IF(M45="","",M45*T45)
E46: Vinyl Rolling Door 12' 6412 (4p) | H46: 2345 | J46: =IF(C46="","",C46*H46) | O46: Structural Mullion for multi-unit | T46: 90 | V46: =IF(M46="","",M46*T46) | AD46: 40
E47: 5" Rail (per panel) | H47: 90 | J47: =IF(C47="","",C47*H47) | O47: Standard Cutback | T47: 50 | V47: =IF(M47="","",M47*T47) | AD47: 25
E48: 7" Rail / French (per panel) | H48: 180 | J48: =IF(C48="","",C48*H48) | O48: Wood Casing Cutback | T48: 80 | V48: =IF(M48="","",M48*T48)
E49: 8' Height (per panel) | H49: 90 | J49: =IF(C49="","",C49*H49) | O49: Install Exterior Capping | T49: 125 | V49: =IF(M49="","",M49*T49)
E50: SolarZone Low-E & Argon (per panel) | H50: 115 | J50: =IF(C50="","",C50*H50) | O50: Install Vinyl Int/Ext Trim | T50: 40 | V50: =IF(M50="","",M50*T50)
E51: SolarZone Low-E Elite (per panel) | H51: 135 | J51: =IF(C51="","",C51*H51) | O51: Special Shape Trim | T51: 40 | V51: =IF(M51="","",M51*T51)
E52: TG2 PriME-Elite (per panel) | H52: 289 | J52: =IF(C52="","",C52*H52) | O52: Header Flashing | T52: 12 | V52: =IF(M52="","",M52*T52)
E53: TK2 Plus- Elite (per panel) | H53: 450 | J53: =IF(C53="","",C53*H53) | O53: 2nd Story Charge | T53: 10 | V53: =IF(M53="","",M53*T53)
E54: Colonial Grids (per panel) | H54: 60 | J54: =IF(C54="","",C54*H54) | O54: Bay Window Finish & Trim | T54: 300 | V54: =IF(M54="","",M54*T54)
E55: Beige/ Clay (per panel) | H55: 95 | J55: =IF(C55="","",C55*H55) | O55: Repair Sill OR Jamb | T55: $25 / Ft | V55: =IF(M55="","",M55*25)
E56: Vinyl Patio Door Trim | H56: 95 | J56: =IF(C56="","",C56*H56) | O56: J-Channel | T56: 40 | V56: =IF(M56="","",M56*T56)
E57: Integrated Mini Blinds | J57: =IF(C57="","",C57*H57) | O57: Clear Story | V57: =IF(M57="","",M57*T57)
E58: Exterior Color (Exterior Surface Only) | J58: =IF(C58="","",C58*H58) | O58: Maintenance Agreement | V58: =IF(M58="","",M58*T58)
E59: ______________________________ | J59: =IF(C59="","",C59*H59)
J60: =IF(C60="","",C60*H60)
B61: Window World agrees to install windows and doors as noted above and on the attached order form and to perform other services as specified above for the price quoted on this form. No other promises, expressed or implied, are made except those expressed in writing on this agreement. If Window World seeks legal counsel to enforce obligations under this contract, Customer agrees to pay reasonable attorneys fees and costs. | H61: The buyer is responsible for: - Securing permits, unless noted on the contract. - Removal and re-installation of any existing security system, burglar bars, A/C units, window coverings, and/or obstructions prior to installation. Additional charges for removing items are at the following rates: A/C Unit-$50; Curtains/Blinds-$25/Window; Furniture-$10/Item; Shutters-$50 each. INITIALS: __________ | Q61: NOTICE OF CANCELLATION You the buyer may cancel this transaction at any time prior to midnight of the third business day after the date of this transaction. Notice of cancellation must be in writing postmarked no later than midnight of the following third business day. INITIALS: _______
B71: THIS IS A CUSTOM ORDER NOT FOR RESALE! . Windows that are unclaimed after 12 months will be deemed abandoned and will remain property of Window World.
B72: No extra work if not in writing! | T72: Customer Agrees to the terms of payment as follows:
S73: Total List Price $ | T73: =SUM(J15:J16,J20:J26,J28:J32,J43:J60,V14,V16:V30,V32:V34,V36:V39,V41:V60) -> 0
S74: Administrative & Setup Fee $ 150 $ | T74: 150 | Y74: 0
S75: Sales Tax (MS Only - 7%) $ | Y75: 75
K76: CK # | S76: Total Amount $ | T76: =SUM(T73:T75,T80) -> 150 | Y76: 125
S77: Custom Order Deposit 50% $ | T77: =0.5*JobAmount -> 75
S78: Balance Paid to Installer upon Completion $ | T78: =JobAmount-T77 -> 75
S79: Amt Financed $
S80: Contribute to St. Jude $
O83: VISA AMEX M/C DISC # | S83: Exp. Date | V83: Sec. Code
C84: 959 | D84: Heath Manuel 225-472-3007 | H84: =TODAY() -> 46156 | T84: =TODAY() -> 46156
C86: Emp. # | E86: Estimator | H86: Date | K86: Owner | T86: Date
T87: =TODAY() -> 46156
C88: Window World of Baton Rouge, LLC d/b/a Window World, World of Windows
K89: Owner | T89: Date
C112: Window World of Baton Rouge, LLC d/b/a Window World, World of Windows | K112: Owner | T112: Date
C113: Form # LC-WC-1102 | V113: Revised 11/07/2024

Sheet Warranty
B3: All Inclusive Transferable Lifetime Warranty
B52: Installation Warranty
B73: WAIVER OF MAINTENANCE AGREEMENT

Sheet Order Form
S9: PO# | AA9: ACCT # | AB9: =Contract!K10 -> 0 | AG9: ORDER DATE:
S13: =Contract!F9 -> 0 | AF13: Phone: | AG13: =[0]!WorkPhone -> 0
S14: Customer: | AF14: Phone: | AG14: =[0]!CellPhone -> 0
S15: =Contract!F10 -> 0 | AD15: =Contract!F11 -> 0 | AK15: =Contract!L11 -> 0
S16: Address | AD16: City | AK16: Zip
W18: Ned Pearson | AG18: 225-328-2500
S19: Estimator: | AF19: Phone:
C23: QTY | D23: MODEL | E23: VINYL | F23: INT | G23: EXT | H23: MFG SIZE | L23: CUSTOM | N23: WINDOW | P23: GLASS | Q23: FOAM | R23: GRID OPTIONS | U23: OBSC | X23: TEMP | Y23: NAIL FIN | Z23: NAIL FIN | AA23: FULL | AB23: ORIEL | AC23: HDR | AD23: FOAM | AF23: TYPE | AG23: TYPE | AH23: TYPE | AK23: TYPE | AL23: SILL | AP23: ALUM | AQ23: STEEL | AR23: WINDOW | AS23: WINDOW | AT23: WINDOW | AU23: DOOR | AV23: DOOR | AW23: DOOR
E24: COLOR | F24: COLOR | G24: COLOR | H24: WIDTH | I24: X | J24: HEIGHT | K24: LEG HEIGHT | L24: RADIUS | N24: NUMBER | O24: HINGE | P24: OPTION | Q24: ENHANCED | R24: STYLE | S24: PATTERN | U24: FULL- BSO | X24: FUL-BSO | Y24: NO J | Z24: WITH J | AA24: SCREEN | AB24: DIM | AC24: FLASH | AD24: EXP | AF24: Ext. | AG24: Trim | AH24: Remove | AK24: Install | AL24: Repair | AP24: STUCCO | AQ24: STUCCO | AR24: LE | AS24: LEE | AT24: GRID | AU24: LE | AV24: LEE | AW24: GRID
G26: LO | AF26: BRICK | AG26: VINYL | AH26: ALUM | AK26: IN | AL26: Yes
G27: DO | AF27: ALUM | AG27: CAP | AH27: STEEL | AK27: OUT | AL27: No
G28: CH | AF28: STUCCO | AG28: F&T | AH28: STORM | AK28: EXT | AL28: .
E29: WH | G29: WH | AF29: WOOD | AG29: . | AH29: WOOD | AK29: . | AL29: .
E30: BG | G30: FW | L30: MULL UNIT CONSISTING OF | P30: LE | AF30: . | AG30: . | AH30: . | AK30: . | AL30: .
B31: 1 | I31: x | M31: =IF(D31="","",LEFT(D31,1)) | P31: =IF(D31="","",IF(LEFT(D31,1)="M","",IF(SolarZoneLeeQty<>"","LEE",IF(SolarZoneLeQty<>"","LE","")))) | AC31: =IF(D31="","",IF(LEFT(D31,1)="M","","Y")) | AP31: =IF(AND(AH31="ALUM",AF31="STUCCO"),C31,0) -> 0 | AQ31: =IF(AND(AH31="STEEL",AF31="STUCCO"),C31,0) -> 0 | AR31: =IF(AND(LEFT(D31,1)<>"6",P31="LE"),C31,0) -> 0 | AS31: =IF(AND(LEFT(D31,1)<>"6",P31="LEE"),C31,0) -> 0 | AT31: =IF(AND(LEFT(D31,1)<>"6",R31>""),C31,0) -> 0 | AU31: =IF(AND(LEFT(D31,1)="6",P31="LE"),C31,0) -> 0 | AV31: =IF(AND(LEFT(D31,1)="6",P31="LEE"),C31,0) -> 0 | AW31: =IF(AND(LEFT(D31,1)="6",R31>""),C31,0) -> 0
B32: 2 | E32: =IF(D32="","",IF(LEFT(D32,1)="M","",IF(BeigeColorQty>0,"BG","WH"))) | I32: x | M32: =IF(D32="","",LEFT(D32,1)) | P32: =IF(D32="","",IF(LEFT(D32,1)="M","",IF(SolarZoneLeeQty<>"","LEE",IF(SolarZoneLeQty<>"","LE","")))) | AC32: =IF(D32="","",IF(LEFT(D32,1)="M","","Y")) | AF32: =IF(D32="","",IF(LEFT(D32,1)="M","",AF31)) | AG32: =IF(D32="","",IF(LEFT(D32,1)="M","",AG31)) | AH32: =IF(D32="","",IF(LEFT(D32,1)="M","",AH31)) | AK32: =IF(D32="","",IF(LEFT(D32,1)="M","",AK31)) | AP32: =IF(AND(AH32="ALUM",AF32="STUCCO"),C32,0) -> 0 | AQ32: =IF(AND(AH32="STEEL",AF32="STUCCO"),C32,0) -> 0 | AR32: =IF(AND(LEFT(D32,1)<>"6",P32="LE"),C32,0) -> 0 | AS32: =IF(AND(LEFT(D32,1)<>"6",P32="LEE"),C32,0) -> 0 | AT32: =IF(AND(LEFT(D32,1)<>"6",R32>""),C32,0) -> 0 | AU32: =IF(AND(LEFT(D32,1)="6",P32="LE"),C32,0) -> 0 | AV32: =IF(AND(LEFT(D32,1)="6",P32="LEE"),C32,0) -> 0 | AW32: =IF(AND(LEFT(D32,1)="6",R32>""),C32,0) -> 0
B33: 3 | E33: =IF(D33="","",IF(LEFT(D33,1)="M","",IF(BeigeColorQty>0,"BG","WH"))) | I33: x | M33: =IF(D33="","",LEFT(D33,1)) | P33: =IF(D33="","",IF(LEFT(D33,1)="M","",IF(SolarZoneLeeQty<>"","LEE",IF(SolarZoneLeQty<>"","LE","")))) | AC33: =IF(D33="","",IF(LEFT(D33,1)="M","","Y")) | AF33: =IF(D33="","",IF(LEFT(D33,1)="M","",AF32)) | AG33: =IF(D33="","",IF(LEFT(D33,1)="M","",AG32)) | AH33: =IF(D33="","",IF(LEFT(D33,1)="M","",AH32)) | AK33: =IF(D33="","",IF(LEFT(D33,1)="M","",AK32)) | AP33: =IF(AND(AH33="ALUM",AF33="STUCCO"),C33,0) -> 0 | AQ33: =IF(AND(AH33="STEEL",AF33="STUCCO"),C33,0) -> 0 | AR33: =IF(AND(LEFT(D33,1)<>"6",P33="LE"),C33,0) -> 0 | AS33: =IF(AND(LEFT(D33,1)<>"6",P33="LEE"),C33,0) -> 0 | AT33: =IF(AND(LEFT(D33,1)<>"6",R33>""),C33,0) -> 0 | AU33: =IF(AND(LEFT(D33,1)="6",P33="LE"),C33,0) -> 0 | AV33: =IF(AND(LEFT(D33,1)="6",P33="LEE"),C33,0) -> 0 | AW33: =IF(AND(LEFT(D33,1)="6",R33>""),C33,0) -> 0
B34: 4 | E34: =IF(D34="","",IF(LEFT(D34,1)="M","",IF(BeigeColorQty>0,"BG","WH"))) | I34: x | M34: =IF(D34="","",LEFT(D34,1)) | P34: =IF(D34="","",IF(LEFT(D34,1)="M","",IF(SolarZoneLeeQty<>"","LEE",IF(SolarZoneLeQty<>"","LE","")))) | AC34: =IF(D34="","",IF(LEFT(D34,1)="M","","Y")) | AF34: =IF(D34="","",IF(LEFT(D34,1)="M","",AF33)) | AG34: =IF(D34="","",IF(LEFT(D34,1)="M","",AG33)) | AH34: =IF(D34="","",IF(LEFT(D34,1)="M","",AH33)) | AK34: =IF(D34="","",IF(LEFT(D34,1)="M","",AK33)) | AP34: =IF(AND(AH34="ALUM",AF34="STUCCO"),C34,0) -> 0 | AQ34: =IF(AND(AH34="STEEL",AF34="STUCCO"),C34,0) -> 0 | AR34: =IF(AND(LEFT(D34,1)<>"6",P34="LE"),C34,0) -> 0 | AS34: =IF(AND(LEFT(D34,1)<>"6",P34="LEE"),C34,0) -> 0 | AT34: =IF(AND(LEFT(D34,1)<>"6",R34>""),C34,0) -> 0 | AU34: =IF(AND(LEFT(D34,1)="6",P34="LE"),C34,0) -> 0 | AV34: =IF(AND(LEFT(D34,1)="6",P34="LEE"),C34,0) -> 0 | AW34: =IF(AND(LEFT(D34,1)="6",R34>""),C34,0) -> 0
B35: 5 | E35: =IF(D35="","",IF(LEFT(D35,1)="M","",IF(BeigeColorQty>0,"BG","WH"))) | I35: x | M35: =IF(D35="","",LEFT(D35,1)) | P35: =IF(D35="","",IF(LEFT(D35,1)="M","",IF(SolarZoneLeeQty<>"","LEE",IF(SolarZoneLeQty<>"","LE","")))) | AC35: =IF(D35="","",IF(LEFT(D35,1)="M","","Y")) | AF35: =IF(D35="","",IF(LEFT(D35,1)="M","",AF34)) | AG35: =IF(D35="","",IF(LEFT(D35,1)="M","",AG34)) | AH35: =IF(D35="","",IF(LEFT(D35,1)="M","",AH34)) | AK35: =IF(D35="","",IF(LEFT(D35,1)="M","",AK34)) | AP35: =IF(AND(AH35="ALUM",AF35="STUCCO"),C35,0) -> 0 | AQ35: =IF(AND(AH35="STEEL",AF35="STUCCO"),C35,0) -> 0 | AR35: =IF(AND(LEFT(D35,1)<>"6",P35="LE"),C35,0) -> 0 | AS35: =IF(AND(LEFT(D35,1)<>"6",P35="LEE"),C35,0) -> 0 | AT35: =IF(AND(LEFT(D35,1)<>"6",R35>""),C35,0) -> 0 | AU35: =IF(AND(LEFT(D35,1)="6",P35="LE"),C35,0) -> 0 | AV35: =IF(AND(LEFT(D35,1)="6",P35="LEE"),C35,0) -> 0 | AW35: =IF(AND(LEFT(D35,1)="6",R35>""),C35,0) -> 0
B36: 6 | E36: =IF(D36="","",IF(LEFT(D36,1)="M","",IF(BeigeColorQty>0,"BG","WH"))) | I36: x | M36: =IF(D36="","",LEFT(D36,1)) | P36: =IF(D36="","",IF(LEFT(D36,1)="M","",IF(SolarZoneLeeQty<>"","LEE",IF(SolarZoneLeQty<>"","LE","")))) | AC36: =IF(D36="","",IF(LEFT(D36,1)="M","","Y")) | AF36: =IF(D36="","",IF(LEFT(D36,1)="M","",AF35)) | AG36: =IF(D36="","",IF(LEFT(D36,1)="M","",AG35)) | AH36: =IF(D36="","",IF(LEFT(D36,1)="M","",AH35)) | AK36: =IF(D36="","",IF(LEFT(D36,1)="M","",AK35)) | AP36: =IF(AND(AH36="ALUM",AF36="STUCCO"),C36,0) -> 0 | AQ36: =IF(AND(AH36="STEEL",AF36="STUCCO"),C36,0) -> 0 | AR36: =IF(AND(LEFT(D36,1)<>"6",P36="LE"),C36,0) -> 0 | AS36: =IF(AND(LEFT(D36,1)<>"6",P36="LEE"),C36,0) -> 0 | AT36: =IF(AND(LEFT(D36,1)<>"6",R36>""),C36,0) -> 0 | AU36: =IF(AND(LEFT(D36,1)="6",P36="LE"),C36,0) -> 0 | AV36: =IF(AND(LEFT(D36,1)="6",P36="LEE"),C36,0) -> 0 | AW36: =IF(AND(LEFT(D36,1)="6",R36>""),C36,0) -> 0
B37: 7 | E37: =IF(D37="","",IF(LEFT(D37,1)="M","",IF(BeigeColorQty>0,"BG","WH"))) | I37: x | M37: =IF(D37="","",LEFT(D37,1)) | P37: =IF(D37="","",IF(LEFT(D37,1)="M","",IF(SolarZoneLeeQty<>"","LEE",IF(SolarZoneLeQty<>"","LE","")))) | AC37: =IF(D37="","",IF(LEFT(D37,1)="M","","Y")) | AF37: =IF(D37="","",IF(LEFT(D37,1)="M","",AF36)) | AG37: =IF(D37="","",IF(LEFT(D37,1)="M","",AG36)) | AH37: =IF(D37="","",IF(LEFT(D37,1)="M","",AH36)) | AK37: =IF(D37="","",IF(LEFT(D37,1)="M","",AK36)) | AP37: =IF(AND(AH37="ALUM",AF37="STUCCO"),C37,0) -> 0 | AQ37: =IF(AND(AH37="STEEL",AF37="STUCCO"),C37,0) -> 0 | AR37: =IF(AND(LEFT(D37,1)<>"6",P37="LE"),C37,0) -> 0 | AS37: =IF(AND(LEFT(D37,1)<>"6",P37="LEE"),C37,0) -> 0 | AT37: =IF(AND(LEFT(D37,1)<>"6",R37>""),C37,0) -> 0 | AU37: =IF(AND(LEFT(D37,1)="6",P37="LE"),C37,0) -> 0 | AV37: =IF(AND(LEFT(D37,1)="6",P37="LEE"),C37,0) -> 0 | AW37: =IF(AND(LEFT(D37,1)="6",R37>""),C37,0) -> 0
B38: 8 | E38: =IF(D38="","",IF(LEFT(D38,1)="M","",IF(BeigeColorQty>0,"BG","WH"))) | I38: x | M38: =IF(D38="","",LEFT(D38,1)) | P38: =IF(D38="","",IF(LEFT(D38,1)="M","",IF(SolarZoneLeeQty<>"","LEE",IF(SolarZoneLeQty<>"","LE","")))) | AC38: =IF(D38="","",IF(LEFT(D38,1)="M","","Y")) | AF38: =IF(D38="","",IF(LEFT(D38,1)="M","",AF37)) | AG38: =IF(D38="","",IF(LEFT(D38,1)="M","",AG37)) | AH38: =IF(D38="","",IF(LEFT(D38,1)="M","",AH37)) | AK38: =IF(D38="","",IF(LEFT(D38,1)="M","",AK37)) | AP38: =IF(AND(AH38="ALUM",AF38="STUCCO"),C38,0) -> 0 | AQ38: =IF(AND(AH38="STEEL",AF38="STUCCO"),C38,0) -> 0 | AR38: =IF(AND(LEFT(D38,1)<>"6",P38="LE"),C38,0) -> 0 | AS38: =IF(AND(LEFT(D38,1)<>"6",P38="LEE"),C38,0) -> 0 | AT38: =IF(AND(LEFT(D38,1)<>"6",R38>""),C38,0) -> 0 | AU38: =IF(AND(LEFT(D38,1)="6",P38="LE"),C38,0) -> 0 | AV38: =IF(AND(LEFT(D38,1)="6",P38="LEE"),C38,0) -> 0 | AW38: =IF(AND(LEFT(D38,1)="6",R38>""),C38,0) -> 0
B39: 9 | E39: =IF(D39="","",IF(LEFT(D39,1)="M","",IF(BeigeColorQty>0,"BG","WH"))) | I39: x | M39: =IF(D39="","",LEFT(D39,1)) | P39: =IF(D39="","",IF(LEFT(D39,1)="M","",IF(SolarZoneLeeQty<>"","LEE",IF(SolarZoneLeQty<>"","LE","")))) | AC39: =IF(D39="","",IF(LEFT(D39,1)="M","","Y")) | AF39: =IF(D39="","",IF(LEFT(D39,1)="M","",AF38)) | AG39: =IF(D39="","",IF(LEFT(D39,1)="M","",AG38)) | AH39: =IF(D39="","",IF(LEFT(D39,1)="M","",AH38)) | AK39: =IF(D39="","",IF(LEFT(D39,1)="M","",AK38)) | AP39: =IF(AND(AH39="ALUM",AF39="STUCCO"),C39,0) -> 0 | AQ39: =IF(AND(AH39="STEEL",AF39="STUCCO"),C39,0) -> 0 | AR39: =IF(AND(LEFT(D39,1)<>"6",P39="LE"),C39,0) -> 0 | AS39: =IF(AND(LEFT(D39,1)<>"6",P39="LEE"),C39,0) -> 0 | AT39: =IF(AND(LEFT(D39,1)<>"6",R39>""),C39,0) -> 0 | AU39: =IF(AND(LEFT(D39,1)="6",P39="LE"),C39,0) -> 0 | AV39: =IF(AND(LEFT(D39,1)="6",P39="LEE"),C39,0) -> 0 | AW39: =IF(AND(LEFT(D39,1)="6",R39>""),C39,0) -> 0
B40: 10 | E40: =IF(D40="","",IF(LEFT(D40,1)="M","",IF(BeigeColorQty>0,"BG","WH"))) | I40: x | M40: =IF(D40="","",LEFT(D40,1)) | P40: =IF(D40="","",IF(LEFT(D40,1)="M","",IF(SolarZoneLeeQty<>"","LEE",IF(SolarZoneLeQty<>"","LE","")))) | AC40: =IF(D40="","",IF(LEFT(D40,1)="M","","Y")) | AF40: =IF(D40="","",IF(LEFT(D40,1)="M","",AF39)) | AG40: =IF(D40="","",IF(LEFT(D40,1)="M","",AG39)) | AH40: =IF(D40="","",IF(LEFT(D40,1)="M","",AH39)) | AK40: =IF(D40="","",IF(LEFT(D40,1)="M","",AK39)) | AP40: =IF(AND(AH40="ALUM",AF40="STUCCO"),C40,0) -> 0 | AQ40: =IF(AND(AH40="STEEL",AF40="STUCCO"),C40,0) -> 0 | AR40: =IF(AND(LEFT(D40,1)<>"6",P40="LE"),C40,0) -> 0 | AS40: =IF(AND(LEFT(D40,1)<>"6",P40="LEE"),C40,0) -> 0 | AT40: =IF(AND(LEFT(D40,1)<>"6",R40>""),C40,0) -> 0 | AU40: =IF(AND(LEFT(D40,1)="6",P40="LE"),C40,0) -> 0 | AV40: =IF(AND(LEFT(D40,1)="6",P40="LEE"),C40,0) -> 0 | AW40: =IF(AND(LEFT(D40,1)="6",R40>""),C40,0) -> 0
B41: 11 | E41: =IF(D41="","",IF(LEFT(D41,1)="M","",IF(BeigeColorQty>0,"BG","WH"))) | I41: x | M41: =IF(D41="","",LEFT(D41,1)) | P41: =IF(D41="","",IF(LEFT(D41,1)="M","",IF(SolarZoneLeeQty<>"","LEE",IF(SolarZoneLeQty<>"","LE","")))) | AC41: =IF(D41="","",IF(LEFT(D41,1)="M","","Y")) | AF41: =IF(D41="","",IF(LEFT(D41,1)="M","",AF40)) | AG41: =IF(D41="","",IF(LEFT(D41,1)="M","",AG40)) | AH41: =IF(D41="","",IF(LEFT(D41,1)="M","",AH40)) | AK41: =IF(D41="","",IF(LEFT(D41,1)="M","",AK40)) | AP41: =IF(AND(AH41="ALUM",AF41="STUCCO"),C41,0) -> 0 | AQ41: =IF(AND(AH41="STEEL",AF41="STUCCO"),C41,0) -> 0 | AR41: =IF(AND(LEFT(D41,1)<>"6",P41="LE"),C41,0) -> 0 | AS41: =IF(AND(LEFT(D41,1)<>"6",P41="LEE"),C41,0) -> 0 | AT41: =IF(AND(LEFT(D41,1)<>"6",R41>""),C41,0) -> 0 | AU41: =IF(AND(LEFT(D41,1)="6",P41="LE"),C41,0) -> 0 | AV41: =IF(AND(LEFT(D41,1)="6",P41="LEE"),C41,0) -> 0 | AW41: =IF(AND(LEFT(D41,1)="6",R41>""),C41,0) -> 0
B42: 12 | E42: =IF(D42="","",IF(LEFT(D42,1)="M","",IF(BeigeColorQty>0,"BG","WH"))) | I42: x | M42: =IF(D42="","",LEFT(D42,1)) | P42: =IF(D42="","",IF(LEFT(D42,1)="M","",IF(SolarZoneLeeQty<>"","LEE",IF(SolarZoneLeQty<>"","LE","")))) | AC42: =IF(D42="","",IF(LEFT(D42,1)="M","","Y")) | AF42: =IF(D42="","",IF(LEFT(D42,1)="M","",AF41)) | AG42: =IF(D42="","",IF(LEFT(D42,1)="M","",AG41)) | AH42: =IF(D42="","",IF(LEFT(D42,1)="M","",AH41)) | AK42: =IF(D42="","",IF(LEFT(D42,1)="M","",AK41)) | AP42: =IF(AND(AH42="ALUM",AF42="STUCCO"),C42,0) -> 0 | AQ42: =IF(AND(AH42="STEEL",AF42="STUCCO"),C42,0) -> 0 | AR42: =IF(AND(LEFT(D42,1)<>"6",P42="LE"),C42,0) -> 0 | AS42: =IF(AND(LEFT(D42,1)<>"6",P42="LEE"),C42,0) -> 0 | AT42: =IF(AND(LEFT(D42,1)<>"6",R42>""),C42,0) -> 0 | AU42: =IF(AND(LEFT(D42,1)="6",P42="LE"),C42,0) -> 0 | AV42: =IF(AND(LEFT(D42,1)="6",P42="LEE"),C42,0) -> 0 | AW42: =IF(AND(LEFT(D42,1)="6",R42>""),C42,0) -> 0
B43: 13 | E43: =IF(D43="","",IF(LEFT(D43,1)="M","",IF(BeigeColorQty>0,"BG","WH"))) | I43: x | M43: =IF(D43="","",LEFT(D43,1)) | P43: =IF(D43="","",IF(LEFT(D43,1)="M","",IF(SolarZoneLeeQty<>"","LEE",IF(SolarZoneLeQty<>"","LE","")))) | AC43: =IF(D43="","",IF(LEFT(D43,1)="M","","Y")) | AF43: =IF(D43="","",IF(LEFT(D43,1)="M","",AF42)) | AG43: =IF(D43="","",IF(LEFT(D43,1)="M","",AG42)) | AH43: =IF(D43="","",IF(LEFT(D43,1)="M","",AH42)) | AK43: =IF(D43="","",IF(LEFT(D43,1)="M","",AK42)) | AP43: =IF(AND(AH43="ALUM",AF43="STUCCO"),C43,0) -> 0 | AQ43: =IF(AND(AH43="STEEL",AF43="STUCCO"),C43,0) -> 0 | AR43: =IF(AND(LEFT(D43,1)<>"6",P43="LE"),C43,0) -> 0 | AS43: =IF(AND(LEFT(D43,1)<>"6",P43="LEE"),C43,0) -> 0 | AT43: =IF(AND(LEFT(D43,1)<>"6",R43>""),C43,0) -> 0 | AU43: =IF(AND(LEFT(D43,1)="6",P43="LE"),C43,0) -> 0 | AV43: =IF(AND(LEFT(D43,1)="6",P43="LEE"),C43,0) -> 0 | AW43: =IF(AND(LEFT(D43,1)="6",R43>""),C43,0) -> 0
... B54: 24 | E54: =IF(D54="","",IF(LEFT(D54,1)="M","",IF(BeigeColorQty>0,"BG","WH"))) | I54: x | M54: =IF(D54="","",LEFT(D54,1)) | P54: =IF(D54="","",IF(LEFT(D54,1)="M","",IF(SolarZoneLeeQty<>"","LEE",IF(SolarZoneLeQty<>"","LE","")))) | AC54: =IF(D54="","",IF(LEFT(D54,1)="M","","Y")) | AF54: =IF(D54="","",IF(LEFT(D54,1)="M","",AF53)) | AG54: =IF(D54="","",IF(LEFT(D54,1)="M","",AG53)) | AH54: =IF(D54="","",IF(LEFT(D54,1)="M","",AH53)) | AK54: =IF(D54="","",IF(LEFT(D54,1)="M","",AK53)) | AP54: =IF(AND(AH54="ALUM",AF54="STUCCO"),C54,0) -> 0 | AQ54: =IF(AND(AH54="STEEL",AF54="STUCCO"),C54,0) -> 0 | AR54: =IF(AND(LEFT(D54,1)<>"6",P54="LE"),C54,0) -> 0 | AS54: =IF(AND(LEFT(D54,1)<>"6",P54="LEE"),C54,0) -> 0 | AT54: =IF(AND(LEFT(D54,1)<>"6",R54>""),C54,0) -> 0 | AU54: =IF(AND(LEFT(D54,1)="6",P54="LE"),C54,0) -> 0 | AV54: =IF(AND(LEFT(D54,1)="6",P54="LEE"),C54,0) -> 0 | AW54: =IF(AND(LEFT(D54,1)="6",R54>""),C54,0) -> 0
B55: I certify the salesperson has explained and identified each and every abbreviation, | R55: =" NOTES: " -> NOTES:
B56: term, and drawing on this page to my full and complete understanding including how
B57: each and every window is removed, installed, trimmed, accessorized, and warranted.
C60: OWNER | N60: DATE | R60: White Copy - Original Yellow Copy - Estimator Pink Copy - Customer | AK60: PAGE 1 OF
C66: =SUMIF(ModelRange,"0201",NumWinsRange) -> 0 | D66: Model0201
C67: =SUMIF(ModelRange,"0202",NumWinsRange) -> 0 | D67: Model0202
C68: =SUMIF(ModelRange,"0203",NumWinsRange) -> 0 | D68: Model0203
C69: =SUMIF(ModelRange,"0204",NumWinsRange) -> 0 | D69: Model0204
C70: =SUMIF(ModelRange,"0209",NumWinsRange) -> 0 | D70: Model0209
C71: =SUMIF(ModelRange,"0401",NumWinsRange) -> 0 | D71: Model0401
C72: =SUMIF(ModelRange,"0402",NumWinsRange) -> 0 | D72: Model0402
C73: =SUMIF(ModelRange,"0403",NumWinsRange) -> 0 | D73: Model0403
C74: =SUMIF(ModelRange,"0404",NumWinsRange) -> 0 | D74: Model0404
C75: =SUMIF(ModelRange,"0409",NumWinsRange) -> 0 | D75: Model0409
C76: =SUMIF(ModelRange,"0501",NumWinsRange) -> 0 | D76: Model0501
C77: =SUMIF(ModelRange,"0502",NumWinsRange) -> 0 | D77: Model0502
C78: =SUMIF(ModelRange,"0503",NumWinsRange) -> 0 | D78: Model0503
C79: =SUMIF(ModelRange,"0504",NumWinsRange) -> 0 | D79: Model0504
C80: =SUMIF(ModelRange,"0509",NumWinsRange) -> 0 | D80: Model0509
C81: =SUMIF(ModelRange,"0522",NumWinsRange) -> 0 | D81: Model0522
C82: =SUMIF(ModelRange,"0523",NumWinsRange) -> 0 | D82: Model0523
C83: =SUMIF(ModelRange,"0529",NumWinsRange) -> 0 | D83: Model0529
C84: =SUMIF(ModelRange,"0601",NumWinsRange) -> 0 | D84: Model0601
C85: =SUMIF(ModelRange,"0602",NumWinsRange) -> 0 | D85: Model0602
C86: =SUMIF(ModelRange,"0603",NumWinsRange) -> 0 | D86: Model0603
C87: =SUMIF(ModelRange,"0609",NumWinsRange) -> 0 | D87: Model0609
C88: =SUMIF(ModelRange,"0614",NumWinsRange) -> 0 | D88: Model0614
C89: =SUMIF(ModelRange,"0901",NumWinsRange) -> 0 | D89: Model0901
C90: =SUMIF(ModelRange,"0902",NumWinsRange) -> 0 | D90: Model0902
C91: =SUMIF(ModelRange,"0903",NumWinsRange) -> 0 | D91: Model0903
C92: =SUMIF(ModelRange,"0909",NumWinsRange) -> 0 | D92: Model0909
C93: =SUMIF(ModelRange,"0914",NumWinsRange) -> 0 | D93: Model0914
C94: =SUMIF(ModelRange,"0951",NumWinsRange) -> 0 | D94: Model0951
C95: =SUMIF(ModelRange,"0952",NumWinsRange) -> 0 | D95: Model0952
C96: =SUMIF(ModelRange,"0954",NumWinsRange) -> 0 | D96: Model0954
C97: =SUMIF(ModelRange,"0955",NumWinsRange) -> 0 | D97: Model0955
C98: =SUMIF(ModelRange,"0970",NumWinsRange) -> 0 | D98: Model0970
C99: =SUMIF(ModelRange,"0971",NumWinsRange) -> 0 | D99: Model0971
C100: =SUMIF(ModelRange,"0972",NumWinsRange) -> 0 | D100: Model0972
C101: =SUMIF(ModelRange,"0973",NumWinsRange) -> 0 | D101: Model0973
C102: =SUMIF(ModelRange,"0979",NumWinsRange) -> 0 | D102: Model0979
C103: =SUMIF(ModelRange,"6105",NumWinsRange) -> 0 | D103: Model6105
C104: =SUMIF(ModelRange,"6106",NumWinsRange) -> 0 | D104: Model6106
C105: =SUMIF(ModelRange,"6108",NumWinsRange) -> 0 | D105: Model6108
C106: =SUMIF(ModelRange,"6109",NumWinsRange) -> 0 | D106: Model6109
C107: =SUMIF(ModelRange,"6112",NumWinsRange) -> 0 | D107: Model6112
C108: =SUMIF(ModelRange,"6122",NumWinsRange) -> 0 | D108: Model6122
C109: =SUMIF(ModelRange,"S105",NumWinsRange) -> 0 | D109: ModelS105
C110: =SUMIF(ModelRange,"S110",NumWinsRange) -> 0 | D110: ModelS110
C111: =SUMIF(ModelRange,"S111",NumWinsRange) -> 0 | D111: ModelS111
C112: =SUMIF(ModelRange,"S112",NumWinsRange) -> 0 | D112: ModelS112
C113: =SUMIF(ModelRange,"S113",NumWinsRange) -> 0 | D113: ModelS113
C114: =SUMIF(ModelRange,"S114",NumWinsRange) -> 0 | D114: ModelS114
C115: =SUMIF(ModelRange,"S115",NumWinsRange) -> 0 | D115: ModelS115
C116: =SUMIF(ModelRange,"S116",NumWinsRange) -> 0 | D116: ModelS116
C117: =SUMIF(ModelRange,"S117",NumWinsRange) -> 0 | D117: ModelS117
C118: =SUMIF(ModelRange,"S118",NumWinsRange) -> 0 | D118: ModelS118
C119: =SUMIF(ModelRange,"S119",NumWinsRange) -> 0 | D119: ModelS119
C120: =SUMIF(ModelRange,"S120",NumWinsRange) -> 0 | D120: ModelS120
C121: =SUMIF(ModelRange,"S121",NumWinsRange) -> 0 | D121: ModelS121
C122: =SUMIF(ModelRange,"S122",NumWinsRange) -> 0 | D122: ModelS122
C123: =SUMIF(ModelRange,"S123",NumWinsRange) -> 0 | D123: ModelS123
C124: =SUMIF(ModelRange,"S124",NumWinsRange) -> 0 | D124: ModelS124
C125: =SUMIF(ModelRange,"S125",NumWinsRange) -> 0 | D125: ModelS125
C126: =SUMIF(ModelRange,"S126",NumWinsRange) -> 0 | D126: ModelS126
C127: =SUMIF(ModelRange,"S127",NumWinsRange) -> 0 | D127: ModelS127
C128: =SUMIF(ModelRange,"S128",NumWinsRange) -> 0 | D128: ModelS128
C129: =SUMIF(ModelRange,"S129",NumWinsRange) -> 0 | D129: ModelS129
C130: =SUMIF(ModelRange,"S130",NumWinsRange) -> 0 | D130: ModelS130
C131: =SUMIF(ModelRange,"S131",NumWinsRange) -> 0 | D131: ModelS131
C132: =SUMIF(ModelRange,"S132",NumWinsRange) -> 0 | D132: ModelS132
C133: =SUMIF(ModelRange,"S133",NumWinsRange) -> 0 | D133: ModelS133
...

Sheet Maintenance Agreement 
A4: MAINTENANCE AGREEMENT
A6: Customer Name: | C6: =CustName -> 0 | F6: Customer ID: | G6: =Contract!K10 -> 0 | H6: Phone #: | I6: =WorkPhone -> 0
A7: Address: | B7: =Contract!F10 -> 0 | E7: City: | F7: =Contract!F11 -> 0 | G7: State: | H7: =Contract!H11 -> LA | I7: Zip: | J7: =Contract!L11 -> 0
A8: # of Windows: | C8: =NumWins -> 0
A9: The service provider, Window World Maintenance Division, agrees to provide maintenance on windows purchased from Window World for seven (7) years from date of completion of the original installation of your Window World windows. Service activities will be performed in accordance with the terms and conditions below. Maintenance agreements purchased after the windows have been installed and outside of the original two (2) year labor warranty will be effective from the purchase date of the maintenance agreement and in effect for five (5) years.
A14: Maintenance Includes:
A15: · Re-seal windows as needed, including resetting windows and repairing trim/caulk if required.
A16: · Replace screen fabric as needed.
A17: · Upon request, assess/maintain operational components of windows. Includes lubricating balances, inspecting weep holes for proper drainage, examining windows for glazing integrity, and checking locks, bulb seals, weather-stripping and vent locks.
A18: · Provide summary of work performed.
A19: · Priority service scheduling.
A20: The fee for the service provided under this agreement shall be $________. Payment is due upon signing. This service is for residential properties only and excludes all commercial properties. The undersigned owner acknowledges and agrees that the information above is correct and complete.
A21: WINDOW WORLD MAINTENANCE TERMS AND CONDITIONS
A22: 1) Pricing: The cost will be tiered based upon the following criteria (please circle):
A23: · $295 for up to 14 windows ordered
A24: · $395 for 15-28 windows ordered
... A30: 6) Any work done by a non-certified Window World installer voids any warranty and/or agreements.
A33: Amount: | D33: Check # | G33: or I authorise Window World to run the following credit card
A35: CC#: | F35: Exp: | H35: CVS:
E37: =TODAY() -> 46156 | J37: =TODAY() -> 46156
A38: Customer Signature | E38: Date | G38: WW Representative Date
J40: Revised: 08/11/2022

Sheet Finance Options
B1: Window World Financing
B4: **Monthly payments rounded up**
A5: Monthly Payment | E5: Plan Options
B8: =ROUNDUP(JobAmount/15,0) -> 10 | D8: 15 Months, Interest Free (Pay in full within 15 months, no interest due)
B12: =ROUNDUP(JobAmount/18,0) -> 9 | D12: 18 Months, Interest Free (Pay in full within 18 months, no interest due)
B16: =ROUNDUP((JobAmount*0.020406),0) -> 4 | D16: 7.99% for 60 Equal Monthly Payments
B19: =ROUNDUP(IF(JobAmount>9999.99,(JobAmount*0.013252),0),0) -> 0 | D19: 9.99% for 120 Equal Monthly Payments ($10,000 Minimum)
B23: Scan Me to Get Pre Approved Now!

Sheet Contractors License

Sheet COI
